MLExtreme/__init__.py
MLExtreme/supervised/__init__.py
MLExtreme/supervised/supervised_utils.py
MLExtreme/supervised/xcovPredictor.py
MLExtreme/unsupervised/__init__.py
MLExtreme/unsupervised/feature_clustering/__init__.py
MLExtreme/unsupervised/feature_clustering/clef.py
MLExtreme/unsupervised/feature_clustering/damex.py
MLExtreme/unsupervised/feature_clustering/utilities.py
MLExtreme/unsupervised/mvsets/__init__.py
MLExtreme/unsupervised/mvsets/mvsets.py
MLExtreme/unsupervised/pca/__init__.py
MLExtreme/unsupervised/pca/pca.py
MLExtreme/unsupervised/pca/pca_plot.py
MLExtreme/unsupervised/pca/pca_utils.py
MLExtreme/utils/EVT_basics.py
MLExtreme/utils/__init__.py
MLExtreme/utils/dataset_generation.py
mlextreme-0.1.2.dist-info/METADATA
mlextreme-0.1.2.dist-info/WHEEL
mlextreme-0.1.2.dist-info/top_level.txt
mlextreme-0.1.2.dist-info/RECORD
