Metadata-Version: 2.4
Name: MLExtreme
Version: 0.1.2
Summary: Un petit outil de test
Author: Anne Sabourin
Author-email: pierre-antoine.amiand-leroy@ip-paris.fr
License: MIT
Classifier: Programming Language :: Python :: 3
Classifier: Operating System :: OS Independent
Requires-Python: >=3.7
